xia_mail_sender/__init__.py
xia_mail_sender/sender.cpython-39-darwin.so
xia_mail_sender-0.1.4.dist-info/LICENSE.txt
xia_mail_sender-0.1.4.dist-info/METADATA
xia_mail_sender-0.1.4.dist-info/WHEEL
xia_mail_sender-0.1.4.dist-info/top_level.txt
xia_mail_sender-0.1.4.dist-info/RECORD
